__init__.py
loader.py
main.py
render.py
packer_config_gen-1.3.dist-info/licenses/LICENSE.md
packer_config_gen-1.3.dist-info/METADATA
packer_config_gen-1.3.dist-info/WHEEL
packer_config_gen-1.3.dist-info/entry_points.txt
packer_config_gen-1.3.dist-info/top_level.txt
packer_config_gen-1.3.dist-info/RECORD
