Metadata-Version: 2.4
Name: packer_config_gen
Version: 1.3
Summary: Tool to generate Packer configurations from YAML and Jinja2
Project-URL: Repository, https://github.com/serhii9132/packer-config-gen
Classifier: Development Status :: 4 - Beta
Classifier: Intended Audience :: System Administrators
Classifier: Topic :: System :: Systems Administration
Classifier: Topic :: Software Development :: Build Tools
Classifier: Topic :: Utilities
Classifier: Programming Language :: Python :: 3.13
Requires-Python: >=3.13
License-File: LICENSE.md
Requires-Dist: PyYAML
Requires-Dist: Jinja2
Dynamic: license-file
